labyrinth/__init__.py
labyrinth/__main__.py
labyrinth/generate.py
labyrinth/graph.py
labyrinth/grid.py
labyrinth/maze.py
labyrinth/render.py
labyrinth/solve.py
labyrinth/ui/__init__.py
labyrinth/ui/__main__.py
labyrinth/ui/app.py
labyrinth/ui/colors.py
labyrinth/ui/common.py
labyrinth/ui/menu.py
labyrinth/utils/__init__.py
labyrinth/utils/abc.py
labyrinth/utils/collections.py
labyrinth/utils/event.py
labyrinth_py-1.0.3.dist-info/LICENSE
labyrinth_py-1.0.3.dist-info/METADATA
labyrinth_py-1.0.3.dist-info/WHEEL
labyrinth_py-1.0.3.dist-info/entry_points.txt
labyrinth_py-1.0.3.dist-info/top_level.txt
labyrinth_py-1.0.3.dist-info/RECORD
