Metadata-Version: 2.1
Name: labyrinth-py
Version: 1.0.3
Summary: Generate and solve mazes using various algorithms
Author: William Dye
License: Copyright 2023 William Dye
Project-URL: Repository, https://github.com/will2dye4/labyrinth.git
Keywords: dfs,depth first search,kruskal's algorithm,labyrinth,labyrinth generator,labyrinth gui,labyrinth solver,labyrinth ui,maze,maze generator,maze gui,maze solver,maze ui,prim's algorithm,wilson's algorithm
Requires-Python: >=3.7
License-File: LICENSE
